arcdico/__init__.py
arcdico/arcdico.py
arcdico-1.0.0.dist-info/LICENSE
arcdico-1.0.0.dist-info/WHEEL
arcdico-1.0.0.dist-info/METADATA
arcdico-1.0.0.dist-info/RECORD
