Metadata-Version: 2.1
Name: arcdico
Version: 1.0.0
Summary: Python module to interact with the ArC Instruments Digital Control Module
Home-page: http://www.arc-instruments.co.uk/products/arc-one/
License: MPL-2.0
Author: Spyros Stathopoulos
Author-email: spyros@arc-instruments.co.uk
Requires-Python: >=3.7,<4.0
Classifier: Development Status :: 4 - Beta
Classifier: License :: OSI Approved
Classifier: License :: OSI Approved :: Mozilla Public License 2.0 (MPL 2.0)
Classifier: Programming Language :: Python :: 3
Classifier: Programming Language :: Python :: 3 :: Only
Classifier: Programming Language :: Python :: 3.10
Classifier: Programming Language :: Python :: 3.7
Classifier: Programming Language :: Python :: 3.8
Classifier: Programming Language :: Python :: 3.9
Classifier: Topic :: Scientific/Engineering
Classifier: Topic :: Software Development :: Libraries :: Python Modules
Classifier: Topic :: System :: Hardware
Requires-Dist: pyserial (>=3.0,<4.0)
Project-URL: Bug Tracker, https://github.com/arc-instruments/arc-dico/issues
Project-URL: Repository, https://github.com/arc-instruments/arc-dico
